deutschland/bundeshaushalt/__init__.py
deutschland/bundeshaushalt/api/__init__.py
deutschland/bundeshaushalt/api/budget_data_api.py
deutschland/bundeshaushalt/api_client.py
deutschland/bundeshaushalt/apis/__init__.py
deutschland/bundeshaushalt/configuration.py
deutschland/bundeshaushalt/exceptions.py
deutschland/bundeshaushalt/model/__init__.py
deutschland/bundeshaushalt/model/bad_request.py
deutschland/bundeshaushalt/model/budget_data_response.py
deutschland/bundeshaushalt/model/budget_data_response_meta.py
deutschland/bundeshaushalt/model/budget_data_response_related.py
deutschland/bundeshaushalt/model/budget_element.py
deutschland/bundeshaushalt/model/labeled_element.py
deutschland/bundeshaushalt/model_utils.py
deutschland/bundeshaushalt/models/__init__.py
deutschland/bundeshaushalt/rest.py
de_bundeshaushalt-1.0.0.dist-info/WHEEL
de_bundeshaushalt-1.0.0.dist-info/METADATA
de_bundeshaushalt-1.0.0.dist-info/RECORD
